selene/__init__.py
selene/evaluate_model.py
selene/train_model.py
selene/version.py
selene/interpret/__init__.py
selene/interpret/ism_result.py
selene/interpret/vis.py
selene/interpret/data/gencode_v28_hg19/protein_coding_l12_genes.bed
selene/interpret/data/gencode_v28_hg19/protein_coding_l12_genes.bed.gz
selene/interpret/data/gencode_v28_hg19/protein_coding_l12_genes.bed.gz.tbi
selene/interpret/data/gencode_v28_hg38/protein_coding_l12_genes.bed
selene/interpret/data/gencode_v28_hg38/protein_coding_l12_genes.bed.gz
selene/interpret/data/gencode_v28_hg38/protein_coding_l12_genes.bed.gz.tbi
selene/predict/__init__.py
selene/predict/model_predict.py
selene/predict/predict_handlers/__init__.py
selene/predict/predict_handlers/absolute_diff_score_handler.py
selene/predict/predict_handlers/diff_score_handler.py
selene/predict/predict_handlers/handler.py
selene/predict/predict_handlers/logit_score_handler.py
selene/predict/predict_handlers/write_predictions_handler.py
selene/predict/predict_handlers/write_ref_alt_handler.py
selene/samplers/__init__.py
selene/samplers/bed_file_sampler.py
selene/samplers/intervals_sampler.py
selene/samplers/mat_file_sampler.py
selene/samplers/online_sampler.py
selene/samplers/random_positions_sampler.py
selene/samplers/sampler.py
selene/sequences/__init__.py
selene/sequences/_sequence.cpython-36m-darwin.so
selene/sequences/genome.py
selene/sequences/proteome.py
selene/sequences/sequence.py
selene/targets/__init__.py
selene/targets/_genomic_features.cpython-36m-darwin.so
selene/targets/genomic_features.py
selene/targets/target.py
selene/utils/__init__.py
selene/utils/config.py
selene/utils/config_utils.py
selene/utils/example_model.py
selene/utils/non_strand_specific_module.py
selene/utils/performance_metrics.py
selene/utils/utils.py
selene_sdk/__init__.py
selene_sdk/evaluate_model.py
selene_sdk/train_model.py
selene_sdk/version.py
selene_sdk/interpret/__init__.py
selene_sdk-0.1.0.dist-info/METADATA
selene_sdk-0.1.0.dist-info/RECORD
selene_sdk-0.1.0.dist-info/WHEEL
selene_sdk-0.1.0.dist-info/top_level.txt
