Metadata-Version: 2.1
Name: selene-sdk
Version: 0.1.0
Summary: framework for developing sequence-level deep learning networks
Home-page: https://github.com/FunctionLab/selene
License: UNKNOWN
Platform: UNKNOWN
Classifier: Programming Language :: Python :: 3
Classifier: License :: OSI Approved :: BSD License
Classifier: Topic :: Scientific/Engineering :: Bio-Informatics
Requires-Dist: h5py
Requires-Dist: matplotlib
Requires-Dist: numpy
Requires-Dist: pandas
Requires-Dist: plotly
Requires-Dist: pyfaidx
Requires-Dist: pytabix
Requires-Dist: pyyaml
Requires-Dist: scikit-learn
Requires-Dist: scipy
Requires-Dist: seaborn
Requires-Dist: statsmodels
Requires-Dist: torch (>=0.4.0)
Requires-Dist: torchvision
